nomad_diff/__init__.py
nomad_diff/diff.py
nomad_diff/models.py
nomad_diff-1.0.1.dist-info/LICENSE
nomad_diff-1.0.1.dist-info/METADATA
nomad_diff-1.0.1.dist-info/WHEEL
nomad_diff-1.0.1.dist-info/top_level.txt
nomad_diff-1.0.1.dist-info/RECORD
