Metadata-Version: 2.1
Name: nomad-diff
Version: 1.0.1
Summary: Nomad job diff formatter in Python
Home-page: https://github.com/strigo/nomad-diff
Author: Strigo.io
Author-email: ops@strigo.io
License: MIT
Platform: UNKNOWN
Classifier: License :: OSI Approved :: Apache Software License
Classifier: Programming Language :: Python
Classifier: Programming Language :: Python :: 3
Classifier: Programming Language :: Python :: 3.7
Classifier: Programming Language :: Python :: Implementation :: CPython
Classifier: Topic :: Software Development :: Libraries
Requires-Python: >=3.7
License-File: LICENSE
Requires-Dist: pydantic (~=1.8.2)
Requires-Dist: colorama (~=0.4.4)
